transparentwindow/__init__.py
transparentwindow/_win.py
transparentwindow/capture.py
transparentwindow/posdlg.py
transparentwindow/transparentdlg.py
transparentwindow-0.0.2.dist-info/LICENSE.txt
transparentwindow-0.0.2.dist-info/METADATA
transparentwindow-0.0.2.dist-info/WHEEL
transparentwindow-0.0.2.dist-info/top_level.txt
transparentwindow-0.0.2.dist-info/RECORD
