Metadata-Version: 2.1
Name: transparentwindow
Version: 0.0.2
Summary: A small python library for creating a transparent window.
Home-page: https://github.com/m-m-git/transparentwindow
License: BSD Zero Clause License
Keywords: windows,transparentwindow
Platform: windows
Classifier: Environment :: Win32 (MS Windows)
Classifier: Intended Audience :: Developers
Classifier: License :: OSI Approved
Classifier: Operating System :: Microsoft :: Windows
Classifier: Operating System :: Microsoft :: Windows :: Windows 10
Classifier: Programming Language :: Python :: 3
Classifier: Programming Language :: Python :: Implementation :: CPython
Classifier: Topic :: Software Development :: Libraries
Classifier: Topic :: Software Development :: Libraries :: Python Modules
License-File: LICENSE.txt
Provides-Extra: screencapture
Requires-Dist: numpy ; extra == 'screencapture'
Requires-Dist: opencv-python ; extra == 'screencapture'
Requires-Dist: pillow ; extra == 'screencapture'
